visvasc/__init__.py
visvasc/layout.py
visvasc/site.py
visvasc-0.1.0.dist-info/LICENSE
visvasc-0.1.0.dist-info/WHEEL
visvasc-0.1.0.dist-info/METADATA
visvasc-0.1.0.dist-info/RECORD
